file_api/__init__.py
file_api/file_api.py
file_api-1.0.dist-info/DESCRIPTION.rst
file_api-1.0.dist-info/METADATA
file_api-1.0.dist-info/RECORD
file_api-1.0.dist-info/WHEEL
file_api-1.0.dist-info/metadata.json
file_api-1.0.dist-info/top_level.txt
