Metadata-Version: 2.0
Name: file-api
Version: 1.0
Summary: Client for the Bmat TV/AV file api
Home-page: https://github.com/bmat/file_api
Author: BMAT developers
Author-email: tv-av@bmat.com
License: UNKNOWN
Download-URL: https://github.com/bmat/file_api/archive/master.zip
Keywords: bmat,file,api
Platform: UNKNOWN
Classifier: Topic :: Adaptive Technologies
Classifier: Topic :: Software Development
Classifier: Topic :: System
Classifier: Topic :: Utilities
Requires-Dist: requests (==2.22.0)
